Mbtiler/__init__.py
Mbtiler/cache.py
Mbtiler/filters.py
Mbtiler/proj.py
Mbtiler/setup.py
Mbtiler/sources.py
Mbtiler/tiles.py
Mbtiler/util.py
Mbtiler-2.5.1.dist-info/LICENSE
Mbtiler-2.5.1.dist-info/METADATA
Mbtiler-2.5.1.dist-info/WHEEL
Mbtiler-2.5.1.dist-info/top_level.txt
Mbtiler-2.5.1.dist-info/RECORD
