Metadata-Version: 2.1
Name: Mbtiler
Version: 2.5.1
Summary: Mbtiler is a python toolbox to manipulate map tiles.
Home-page: https://github.com/Elmeslmaney/Mbtiler
Download-URL: http://pypi.python.org/pypi/Mbtiler/
Author: Elmeslmaney
Author-email: mohamedelmeslmaney00@gmail.com
License: LPGL, see LICENSE file.
Keywords: MBTiles,Mapnik
Classifier: Programming Language :: Python :: 3.5
Classifier: Natural Language :: English
Classifier: Topic :: Utilities
Classifier: Development Status :: 5 - Production/Stable
License-File: LICENSE
Requires-Dist: mbutil
Requires-Dist: requests
Provides-Extra: mapnik
Requires-Dist: Mapnik >=2.0.0 ; extra == 'mapnik'
Provides-Extra: pil
Requires-Dist: Pillow ; extra == 'pil'
